ppim/__init__.py
ppim/models/__init__.py
ppim/models/cait.py
ppim/models/cdnv2.py
ppim/models/coat.py
ppim/models/common.py
ppim/models/deit.py
ppim/models/dla.py
ppim/models/hardnet.py
ppim/models/levit.py
ppim/models/lvvit.py
ppim/models/mixer.py
ppim/models/pit.py
ppim/models/pvt.py
ppim/models/rednet.py
ppim/models/repvgg.py
ppim/models/rexnet.py
ppim/models/swin.py
ppim/models/t2t.py
ppim/models/tnt.py
ppim/models/vit.py
ppim-1.1.0.dist-info/LICENSE
ppim-1.1.0.dist-info/METADATA
ppim-1.1.0.dist-info/WHEEL
ppim-1.1.0.dist-info/top_level.txt
ppim-1.1.0.dist-info/RECORD
