Metadata-Version: 2.1
Name: ppim
Version: 1.1.0
Summary: Paddle Image Models
Home-page: UNKNOWN
Author: jm12138
Author-email: 2286040843@qq.com
License: Apache-2.0 License
Platform: UNKNOWN
Requires-Dist: wget
